[

      {
        "sku": "118161",
        "name": "Magnify The Ties That Bind American Pale Lager",
        "brewery": "Magnify Brewing Company",
        "rating": "",
        "category": "Beer",
        "sub_category_1": "Ale",
        "sub_category_2": "Pale Ale",
        "sub_category_3": "American Pale Ale",
        "description": "",
        "region": "Fairfield, New Jersey",
        "country": "United States",
        "abv": "5.20%",
        "ibu": "35",
        "calories_per_serving_12oz": "",
        "carbs_per_serving_12oz": "",
        "tasting_notes": "",
        "food_pairing": "Spicy chicken wings",
        "suggested_glassware": "",
        "serving_temp_f": "",
        "serving_temp_c": "",
        "beer_type": "",
        "features": ""
      },
  
      {
        "sku": "100187",
        "name": "Resident Perky Blonde Ale",
        "brewery": "Resident Brewing Company",
        "rating": "",
        "category": "Beer",
        "sub_category_1": "Ale",
        "sub_category_2": "Golden / Blonde Ale",
        "sub_category_3": "",
        "description": "She’s a perky classic American blonde ale with a slightly sweet finish that is sure to have you coming back for more. Medium dry, crisp, malt forward, did we mention perky?",
        "region": "San Diego, California",
        "country": "United States",
        "abv": "5.20%",
        "ibu": "25",
        "calories_per_serving_12oz": "",
        "carbs_per_serving_12oz": "",
        "tasting_notes": "",
        "food_pairing": "Spicy Thai food",
        "suggested_glassware": "Pint Glass",
        "serving_temp_f": "45-50° F",
        "serving_temp_c": "7.2-10.0° C",
        "beer_type": "",
        "features": ""
      },
      {
        "sku": "100198",
        "name": "Frenzy Yeah, Yeah, Yeah Belgian Style Blonde Ale",
        "brewery": "Frenzy Brewing Company",
        "rating": "",
        "category": "Beer",
        "sub_category_1": "Ale",
        "sub_category_2": "Golden / Blonde Ale",
        "sub_category_3": "",
        "description": "Y3 as we like to call it is crisp and refreshing. The nose is complex with hints of banana and pepper. It's dry finish makes it very drinkable at 7.5%",
        "region": "California",
        "country": "United States",
        "abv": "7.50%",
        "ibu": "25",
        "calories_per_serving_12oz": "",
        "carbs_per_serving_12oz": "",
        "tasting_notes": "Balanced, Banana, Dry, Pepper, Smooth, Yeasty",
        "food_pairing": "Spicy Thai curry",
        "suggested_glassware": "Snifter/Goblet/Chalice",
        "serving_temp_f": "45-50° F",
        "serving_temp_c": "7.2-10.0° C",
        "beer_type": "Craft",
        "features": ""
      },
      {
        "sku": "100201",
        "name": "Golden Road Brewing Dodgers Blonde Ale",
        "brewery": "Golden Road Brewing",
        "rating": "",
        "category": "Beer",
        "sub_category_1": "Ale",
        "sub_category_2": "Golden / Blonde Ale",
        "sub_category_3": "",
        "description": "Thanks for enjoying our beer!\nFor a couple of Kansas City-born Golden Roaders, the idea of developing a new beer with their favorite football team was a dream come true. But like all great endeavors, there must be a shared sense of purpose. In this case, it's passion: passion for beer, passion for sports, but ultimately...passion for the Chiefs. Kingdom Blonde Ale is the collaboration of two fiercely proud and competitive organizations with a common goal in mind: inspiring our fans. Enjoy this bright and tasty brew made for Chiefs fans by Chiefs fans!",
        "region": "Los Angeles, California",
        "country": "United States",
        "abv": "4.80%",
        "ibu": "19",
        "calories_per_serving_12oz": "",
        "carbs_per_serving_12oz": "",
        "tasting_notes": "Crisp, Light, Smooth",
        "food_pairing": "Spicy chicken wings",
        "suggested_glassware": "Pint Glass",
        "serving_temp_f": "45-50° F",
        "serving_temp_c": "7.2-10.0° C",
        "beer_type": "Craft, Seasonal",
        "features": ""
      },
      {
        "sku": "100206",
        "name": "Kona Light Blonde Ale",
        "brewery": "Kona Brewing Company",
        "rating": "5",
        "category": "Beer",
        "sub_category_1": "Ale",
        "sub_category_2": "Golden / Blonde Ale",
        "sub_category_3": "",
        "description": "Refreshing light beer with just 99 calories and crisp tropical flavor that captures the golden moment of island life in every sip.",
        "region": "Hawaii",
        "country": "United States",
        "abv": "7.20%",
        "ibu": "20",
        "calories_per_serving_12oz": "",
        "carbs_per_serving_12oz": "",
        "tasting_notes": "",
        "food_pairing": "Seafood",
        "suggested_glassware": "Pint Glass",
        "serving_temp_f": "45-50° F",
        "serving_temp_c": "7.2-10.0° C",
        "beer_type": "",
        "features": ""
      },
  
      {
        "sku": "100223",
        "name": "Triplehorn Falcon Cloak Blonde Ale",
        "brewery": "Triplehorn",
        "rating": "",
        "category": "Beer",
        "sub_category_1": "Ale",
        "sub_category_2": "Golden / Blonde Ale",
        "sub_category_3": "",
        "description": "Clean, crisp Golden ale. Light hops.",
        "region": "Woodinville, Washington",
        "country": "United States",
        "abv": "6.90%",
        "ibu": "22",
        "calories_per_serving_12oz": "",
        "carbs_per_serving_12oz": "",
        "tasting_notes": "",
        "food_pairing": "Grilled chicken",
        "suggested_glassware": "Pint Glass",
        "serving_temp_f": "45-50° F",
        "serving_temp_c": "7.2-10.0° C",
        "beer_type": "",
        "features": ""
      },
  
        {
          "sku": "134620",
          "name": "Kopernik Pilsner Beer",
          "brewery": "Kopernik Brewing Company",
          "rating": "",
          "category": "Beer",
          "sub_category_1": "Lager",
          "sub_category_2": "Pilsner",
          "sub_category_3": "",
          "description": "",
          "region": "Chicago",
          "country": "United States",
          "abv": "5.00%",
          "ibu": "28",
          "calories_per_serving_12oz": "",
          "carbs_per_serving_12oz": "",
          "tasting_notes": "",
          "food_pairing": "Seafood",
          "suggested_glassware": "",
          "serving_temp_f": "",
          "serving_temp_c": "",
          "beer_type": "",
          "features": ""
        },
        {
          "sku": "134872",
          "name": "10 Barrel Brewing Co Out Of Office Hoppy Pilsner",
          "brewery": "10 Barrel Brewing Co",
          "rating": "",
          "category": "Beer",
          "sub_category_1": "Lager",
          "sub_category_2": "Pilsner",
          "sub_category_3": "",
          "description": "",
          "region": "Oregon",
          "country": "United States",
          "abv": "5.00%",
          "ibu": "35",
          "calories_per_serving_12oz": "",
          "carbs_per_serving_12oz": "",
          "tasting_notes": "",
          "food_pairing": "Spicy Thai food",
          "suggested_glassware": "",
          "serving_temp_f": "",
          "serving_temp_c": "",
          "beer_type": "",
          "features": ""
        },
        {
          "sku": "134873",
          "name": "10 Barrel Brewing Co Pilsner",
          "brewery": "10 Barrel Brewing Co",
          "rating": "",
          "category": "Beer",
          "sub_category_1": "Lager",
          "sub_category_2": "Pilsner",
          "sub_category_3": "",
          "description": "",
          "region": "Oregon",
          "country": "United States",
          "abv": "4.50%",
          "ibu": "35",
          "calories_per_serving_12oz": "",
          "carbs_per_serving_12oz": "",
          "tasting_notes": "",
          "food_pairing": "Spicy Thai food",
          "suggested_glassware": "",
          "serving_temp_f": "",
          "serving_temp_c": "",
          "beer_type": "",
          "features": ""
        },
        {
          "sku": "134874",
          "name": "105 West Brewing 105 West Pilsner",
          "brewery": "105 West Brewing",
          "rating": "",
          "category": "Beer",
          "sub_category_1": "Lager",
          "sub_category_2": "Pilsner",
          "sub_category_3": "",
          "description": "",
          "region": "Castle Rock, Colorado",
          "country": "United States",
          "abv": "5.20%",
          "ibu": "32",
          "calories_per_serving_12oz": "",
          "carbs_per_serving_12oz": "",
          "tasting_notes": "",
          "food_pairing":  "Grilled chicken",
          "suggested_glassware": "",
          "serving_temp_f": "",
          "serving_temp_c": "",
          "beer_type": "",
          "features": ""
        },
        {
          "sku": "134875",
          "name": "12 West Brewing Zona Pilsner",
          "brewery": "12 West Brewing",
          "rating": "",
          "category": "Beer",
          "sub_category_1": "Lager",
          "sub_category_2": "Pilsner",
          "sub_category_3": "",
          "description": "",
          "region": "Mesa, Arizona",
          "country": "United States",
          "abv": "5.20%",
          "ibu": "30",
          "calories_per_serving_12oz": "",
          "carbs_per_serving_12oz": "",
          "tasting_notes": "",
          "food_pairing": "Spicy Thai food",
          "suggested_glassware": "",
          "serving_temp_f": "",
          "serving_temp_c": "",
          "beer_type": "",
          "features": ""
        },
        {
          "sku": "134876",
          "name": "14 Cannons Patient Pilsner",
          "brewery": "14 Cannons Brewing Company",
          "rating": "",
          "category": "Beer",
          "sub_category_1": "Lager",
          "sub_category_2": "Pilsner",
          "sub_category_3": "",
          "description": "",
          "region": "Westlake Village, California",
          "country": "United States",
          "abv": "5.20%",
          "ibu": "35",
          "calories_per_serving_12oz": "",
          "carbs_per_serving_12oz": "",
          "tasting_notes": "",
          "food_pairing": "Salad",
          "suggested_glassware": "",
          "serving_temp_f": "",
          "serving_temp_c": "",
          "beer_type": "",
          "features": ""
        }
      ]

